modules/rx_uart.v
module rx_uart #(
    parameter CLK_FREQ  = 50000000,
    parameter BAUD_RATE = 115200,
    parameter PARITY    = 0,  // 0=NONE, 1=EVEN, 2=ODD
    parameter STOP_BITS = 1   // 1 ou 2
)(
    input  wire       clk_IN,
    input  wire       rst_IN,
    input  wire       rx_IN,

    output reg [7:0]  data_OUT,
    output reg        data_valid_OUT,
    output reg        busy_OUT,
    output reg        parity_error_OUT,
    output reg        frame_error_OUT
);

    localparam CLKS_PER_BIT = CLK_FREQ / BAUD_RATE;
    localparam HALF_BIT     = CLKS_PER_BIT / 2;

    localparam idle  = 3'h0;
    localparam search_start = 3'h1;
    localparam reading_data  = 3'h2;
    localparam parity_search   = 3'h3;
    localparam build_word  = 3'h4;
    localparam finish  = 3'h5;
    reg [2:0] state;
    reg [15:0] clk_count;
    reg [2:0]  bit_index;
    reg [7:0] data_reg;
    reg parity_calc;
    reg parity_bit_rx;
    reg [1:0] stop_count;
	 
    always @(posedge clk_IN) begin
        if (rst_IN) begin
            state <= idle;
            clk_count <= 0;
            bit_index <= 0;
            data_reg <= 0;
            data_OUT <= 0;
            data_valid_OUT <= 0;
            busy_OUT <= 0;
            parity_error_OUT <= 0;
            frame_error_OUT <= 0;
            stop_count <= 0;
        end else begin

            case (state)
                idle: begin
                    data_valid_OUT <= 0;
                    busy_OUT <= 0;
                    parity_error_OUT <= 0;
                    frame_error_OUT <= 0;
                    if (rx_IN == 0) begin
                        busy_OUT <= 1;
                        clk_count <= 0;
                        state <= search_start;
                    end
                end
                search_start: begin
                    if (clk_count < HALF_BIT) begin
                        clk_count <= clk_count + 1;
                    end 
						  else begin
                        clk_count <= 0;
                        if (rx_IN == 0) begin
                            bit_index <= 0;
                            parity_calc <= 0;
                            state <= reading_data;
                        end else begin
                            state <= idle;
                        end
                    end
                end
                reading_data: begin
                    if (clk_count < CLKS_PER_BIT - 1) begin
                        clk_count <= clk_count + 1;
                    end else begin
                        clk_count <= 0;
                        data_reg[bit_index] <= rx_IN;
                        parity_calc <= parity_calc ^ rx_IN;
                        if (bit_index < 7) begin
                            bit_index <= bit_index + 1;
                        end else begin
                            bit_index <= 0;
                            if (PARITY == 0)
                                state <= build_word;
                            else
                                state <= parity_search;
                        end
                    end
                end
                parity_search: begin
                    if (clk_count < CLKS_PER_BIT - 1) begin
                        clk_count <= clk_count + 1;
                    end else begin
                        clk_count <= 0;
                        parity_bit_rx <= rx_IN;
                        if (PARITY == 1)
                            parity_error_OUT <= (parity_calc != rx_IN);
                        else
                            parity_error_OUT <= (parity_calc == rx_IN);
                        state <= build_word;
                        stop_count <= 0;
                    end
		end
                build_word: begin
                    if (clk_count < CLKS_PER_BIT - 1) begin
                        clk_count <= clk_count + 1;
                    end else begin
                        clk_count <= 0;
                        if (rx_IN != 1)
                            frame_error_OUT <= 1;
                        if (stop_count < STOP_BITS - 1) begin
                            stop_count <= stop_count + 1;
                        end else begin
                            data_OUT <= data_reg;
                            data_valid_OUT <= 1;
                            state <= finish;
                        end
                    end
                end
                finish: begin
                    state <= idle;
                end
            endcase
        end
    end

endmodule

tb/rx_uart_tb.v
`timescale 1ns/1ps

module rx_uart_tb;

    localparam CLK_FREQ  = 50000000;   // 10 MHz (simulação mais rápida)
    localparam BAUD_RATE = 115200;

    localparam CLKS_PER_BIT = CLK_FREQ / BAUD_RATE;
    localparam BIT_PERIOD   = CLKS_PER_BIT * 20;

    reg clk;
    reg rst;
    reg rx;

    wire [7:0] data_out;
    wire data_valid;
    wire busy;
    wire parity_error;
    wire frame_error;

    rx_uart #(
        .CLK_FREQ(CLK_FREQ),
        .BAUD_RATE(BAUD_RATE),
        .PARITY(0),
        .STOP_BITS(1)
    ) dut (
        .clk_IN(clk),
        .rst_IN(rst),
        .rx_IN(rx),

        .data_OUT(data_out),
        .data_valid_OUT(data_valid),
        .busy_OUT(busy),
        .parity_error_OUT(parity_error),
        .frame_error_OUT(frame_error)
    );

    // =========================
    // Clock 10 MHz → 100 ns
    // =========================
    always #10 clk = ~clk;

    // =========================
    // Inicialização
    // =========================
    initial begin	    
        $dumpfile("rx_uart.vcd");
        $dumpvars(0, rx_uart_tb);

        clk = 1;
        rst = 1;
        rx  = 1; // idle UART

        #200;
        rst = 0;

        // Enviar alguns bytes
        send_byte(8'h55); // 01010101
        #(BIT_PERIOD * 3);

        send_byte(8'hA3);
        #(BIT_PERIOD * 3);

        send_byte(8'hF0);
        #(BIT_PERIOD * 3);

        $finish;
    end

    task send_byte(input [7:0] data);
        integer i;
        begin
            rx = 0;
            #(BIT_PERIOD);

            for (i = 0; i < 8; i = i + 1) begin
                rx = data[i];
                #(BIT_PERIOD);
            end

            // STOP bit
            rx = 1;
            #(BIT_PERIOD);
        end
    endtask

    // =========================
    // Monitor
    // =========================
    always @(posedge clk) begin
        if (data_valid) begin
            $display("Recebido: %h | parity_err=%b | frame_err=%b",
                     data_out, parity_error, frame_error);
        end
    end

endmodule

tb/rx_uart.vcd
$date
	Tue Mar 24 21:48:09 2026
$end
$version
	Icarus Verilog
$end
$timescale
	1ps
$end
$scope module rx_uart_tb $end
$var wire 1 ! parity_error $end
$var wire 1 " frame_error $end
$var wire 1 # data_valid $end
$var wire 8 $ data_out [7:0] $end
$var wire 1 % busy $end
$var parameter 32 & BAUD_RATE $end
$var parameter 64 ' BIT_PERIOD $end
$var parameter 32 ( CLKS_PER_BIT $end
$var parameter 32 ) CLK_FREQ $end
$var reg 1 * clk $end
$var reg 1 + rst $end
$var reg 1 , rx $end
$scope module dut $end
$var wire 1 * clk_IN $end
$var wire 1 + rst_IN $end
$var wire 1 , rx_IN $end
$var parameter 32 - BAUD_RATE $end
$var parameter 32 . CLKS_PER_BIT $end
$var parameter 32 / CLK_FREQ $end
$var parameter 32 0 HALF_BIT $end
$var parameter 32 1 PARITY $end
$var parameter 32 2 STOP_BITS $end
$var parameter 3 3 build_word $end
$var parameter 3 4 finish $end
$var parameter 3 5 idle $end
$var parameter 3 6 parity_search $end
$var parameter 3 7 reading_data $end
$var parameter 3 8 search_start $end
$var reg 3 9 bit_index [2:0] $end
$var reg 1 % busy_OUT $end
$var reg 16 : clk_count [15:0] $end
$var reg 8 ; data_OUT [7:0] $end
$var reg 8 < data_reg [7:0] $end
$var reg 1 # data_valid_OUT $end
$var reg 1 " frame_error_OUT $end
$var reg 1 = parity_bit_rx $end
$var reg 1 > parity_calc $end
$var reg 1 ! parity_error_OUT $end
$var reg 3 ? state [2:0] $end
$var reg 2 @ stop_count [1:0] $end
$upscope $end
$scope task send_byte $end
$var reg 8 A data [7:0] $end
$var integer 32 B i [31:0] $end
$upscope $end
$upscope $end
$enddefinitions $end
$comment Show the parameter values. $end
$dumpall
b1 8
b10 7
b11 6
b0 5
b101 4
b100 3
b1 2
b0 1
b11011001 0
b10111110101111000010000000 /
b110110010 .
b11100001000000000 -
b10111110101111000010000000 )
b110110010 (
b10000111101000 '
b11100001000000000 &
$end
#0
$dumpvars
bx B
bx A
b0 @
b0 ?
x>
x=
b0 <
b0 ;
b0 :
b0 9
1,
1+
1*
0%
b0 $
0#
0"
0!
$end
#10000
0*
#20000
1*
#30000
0*
#40000
1*
#50000
0*
#60000
1*
#70000
0*
#80000
1*
#90000
0*
#100000
1*
#110000
0*
#120000
1*
#130000
0*
#140000
1*
#150000
0*
#160000
1*
#170000
0*
#180000
1*
#190000
0*
#200000
b1 ?
1%
1*
0,
b1010101 A
0+
#210000
0*
#220000
b1 :
1*
#230000
0*
#240000
b10 :
1*
#250000
0*
#260000
b11 :
1*
#270000
0*
#280000
b100 :
1*
#290000
0*
#300000
b101 :
1*
#310000
0*
#320000
b110 :
1*
#330000
0*
#340000
b111 :
1*
#350000
0*
#360000
b1000 :
1*
#370000
0*
#380000
b1001 :
1*
#390000
0*
#400000
b1010 :
1*
#410000
0*
#420000
b1011 :
1*
#430000
0*
#440000
b1100 :
1*
#450000
0*
#460000
b1101 :
1*
#470000
0*
#480000
b1110 :
1*
#490000
0*
#500000
b1111 :
1*
#510000
0*
#520000
b10000 :
1*
#530000
0*
#540000
b10001 :
1*
#550000
0*
#560000
b10010 :
1*
#570000
0*
#580000
b10011 :
1*
#590000
0*
#600000
b10100 :
1*
#610000
0*
#620000
b10101 :
1*
#630000
0*
#640000
b10110 :
1*
#650000
0*
#660000
b10111 :
1*
#670000
0*
#680000
b11000 :
1*
#690000
0*
#700000
b11001 :
1*
#710000
0*
#720000
b11010 :
1*
#730000
0*
#740000
b11011 :
1*
#750000
0*
#760000
b11100 :
1*
#770000
0*
#780000
b11101 :
1*
#790000
0*
#800000
b11110 :
1*
#810000
0*
#820000
b11111 :
1*
#830000
0*
#840000
b100000 :
1*
#850000
0*
#860000
b100001 :
1*
#870000
0*
#880000
b100010 :
1*
#890000
0*
#900000
b100011 :
1*
#910000
0*
#920000
b100100 :
1*
#930000
0*
#940000
b100101 :
1*
#950000
0*
#960000
b100110 :
1*
#970000
0*
#980000
b100111 :
1*
#990000
0*
#1000000
b101000 :
1*
#1010000
0*
#1020000
b101001 :
1*
#1030000
0*
#1040000
b101010 :
1*
#1050000
0*
#1060000
b101011 :
1*
#1070000
0*
#1080000
b101100 :
1*
#1090000
0*
#1100000
b101101 :
1*
#1110000
0*
#1120000
b101110 :
1*
#1130000
0*
#1140000
b101111 :
1*
#1150000
0*
#1160000
b110000 :
1*
#1170000
0*
#1180000
b110001 :
1*
#1190000
0*
#1200000
b110010 :
1*
#1210000
0*
#1220000
b110011 :
1*
#1230000
0*
#1240000
b110100 :
1*
#1250000
0*
#1260000
b110101 :
1*
#1270000
0*
#1280000
b110110 :
1*
#1290000
0*
#1300000
b110111 :
1*
#1310000
0*
#1320000
b111000 :
1*
#1330000
0*
#1340000
b111001 :
1*
#1350000
0*
#1360000
b111010 :
1*
#1370000
0*
#1380000
b111011 :
1*
#1390000
0*
#1400000
b111100 :
1*
#1410000
0*
#1420000
b111101 :
1*
#1430000
0*
#1440000
b111110 :
1*
#1450000
0*
#1460000
b111111 :
1*
#1470000
0*
#1480000
b1000000 :
1*
#1490000
0*
#1500000
b1000001 :
1*
#1510000
0*
#1520000
b1000010 :
1*
#1530000
0*
#1540000
b1000011 :
1*
#1550000
0*
#1560000
b1000100 :
1*
#1570000
0*
#1580000
b1000101 :
1*
#1590000
0*
#1600000
b1000110 :
1*
#1610000
0*
#1620000
b1000111 :
1*
#1630000
0*
#1640000
b1001000 :
1*
#1650000
0*
#1660000
b1001001 :
1*
#1670000
0*
#1680000
b1001010 :
1*
#1690000
0*
#1700000
b1001011 :
1*
#1710000
0*
#1720000
b1001100 :
1*
#1730000
0*
#1740000
b1001101 :
1*
#1750000
0*
#1760000
b1001110 :
1*
#1770000
0*
#1780000
b1001111 :
1*
#1790000
0*
#1800000
b1010000 :
1*
#1810000
0*
#1820000
b1010001 :
1*
#1830000
0*
#1840000
b1010010 :
1*
#1850000
0*
#1860000
b1010011 :
1*
#1870000
0*
#1880000
b1010100 :
1*
#1890000
0*
#1900000
b1010101 :
1*
#1910000
0*
#1920000
b1010110 :
1*
#1930000
0*
#1940000
b1010111 :
1*
#1950000
0*
#1960000
b1011000 :
1*
#1970000
0*
#1980000
b1011001 :
1*
#1990000
0*
#2000000
b1011010 :
1*
#2010000
0*
#2020000
b1011011 :
1*
#2030000
0*
#2040000
b1011100 :
1*
#2050000
0*
#2060000
b1011101 :
1*
#2070000
0*
#2080000
b1011110 :
1*
#2090000
0*
#2100000
b1011111 :
1*
#2110000
0*
#2120000
b1100000 :
1*
#2130000
0*
#2140000
b1100001 :
1*
#2150000
0*
#2160000
b1100010 :
1*
#2170000
0*
#2180000
b1100011 :
1*
#2190000
0*
#2200000
b1100100 :
1*
#2210000
0*
#2220000
b1100101 :
1*
#2230000
0*
#2240000
b1100110 :
1*
#2250000
0*
#2260000
b1100111 :
1*
#2270000
0*
#2280000
b1101000 :
1*
#2290000
0*
#2300000
b1101001 :
1*
#2310000
0*
#2320000
b1101010 :
1*
#2330000
0*
#2340000
b1101011 :
1*
#2350000
0*
#2360000
b1101100 :
1*
#2370000
0*
#2380000
b1101101 :
1*
#2390000
0*
#2400000
b1101110 :
1*
#2410000
0*
#2420000
b1101111 :
1*
#2430000
0*
#2440000
b1110000 :
1*
#2450000
0*
#2460000
b1110001 :
1*
#2470000
0*
#2480000
b1110010 :
1*
#2490000
0*
#2500000
b1110011 :
1*
#2510000
0*
#2520000
b1110100 :
1*
#2530000
0*
#2540000
b1110101 :
1*
#2550000
0*
#2560000
b1110110 :
1*
#2570000
0*
#2580000
b1110111 :
1*
#2590000
0*
#2600000
b1111000 :
1*
#2610000
0*
#2620000
b1111001 :
1*
#2630000
0*
#2640000
b1111010 :
1*
#2650000
0*
#2660000
b1111011 :
1*
#2670000
0*
#2680000
b1111100 :
1*
#2690000
0*
#2700000
b1111101 :
1*
#2710000
0*
#2720000
b1111110 :
1*
#2730000
0*
#2740000
b1111111 :
1*
#2750000
0*
#2760000
b10000000 :
1*
#2770000
0*
#2780000
b10000001 :
1*
#2790000
0*
#2800000
b10000010 :
1*
#2810000
0*
#2820000
b10000011 :
1*
#2830000
0*
#2840000
b10000100 :
1*
#2850000
0*
#2860000
b10000101 :
1*
#2870000
0*
#2880000
b10000110 :
1*
#2890000
0*
#2900000
b10000111 :
1*
#2910000
0*
#2920000
b10001000 :
1*
#2930000
0*
#2940000
b10001001 :
1*
#2950000
0*
#2960000
b10001010 :
1*
#2970000
0*
#2980000
b10001011 :
1*
#2990000
0*
#3000000
b10001100 :
1*
#3010000
0*
#3020000
b10001101 :
1*
#3030000
0*
#3040000
b10001110 :
1*
#3050000
0*
#3060000
b10001111 :
1*
#3070000
0*
#3080000
b10010000 :
1*
#3090000
0*
#3100000
b10010001 :
1*
#3110000
0*
#3120000
b10010010 :
1*
#3130000
0*
#3140000
b10010011 :
1*
#3150000
0*
#3160000
b10010100 :
1*
#3170000
0*
#3180000
b10010101 :
1*
#3190000
0*
#3200000
b10010110 :
1*
#3210000
0*
#3220000
b10010111 :
1*
#3230000
0*
#3240000
b10011000 :
1*
#3250000
0*
#3260000
b10011001 :
1*
#3270000
0*
#3280000
b10011010 :
1*
#3290000
0*
#3300000
b10011011 :
1*
#3310000
0*
#3320000
b10011100 :
1*
#3330000
0*
#3340000
b10011101 :
1*
#3350000
0*
#3360000
b10011110 :
1*
#3370000
0*
#3380000
b10011111 :
1*
#3390000
0*
#3400000
b10100000 :
1*
#3410000
0*
#3420000
b10100001 :
1*
#3430000
0*
#3440000
b10100010 :
1*
#3450000
0*
#3460000
b10100011 :
1*
#3470000
0*
#3480000
b10100100 :
1*
#3490000
0*
#3500000
b10100101 :
1*
#3510000
0*
#3520000
b10100110 :
1*
#3530000
0*
#3540000
b10100111 :
1*
#3550000
0*
#3560000
b10101000 :
1*
#3570000
0*
#3580000
b10101001 :
1*
#3590000
0*
#3600000
b10101010 :
1*
#3610000
0*
#3620000
b10101011 :
1*
#3630000
0*
#3640000
b10101100 :
1*
#3650000
0*
#3660000
b10101101 :
1*
#3670000
0*
#3680000
b10101110 :
1*
#3690000
0*
#3700000
b10101111 :
1*
#3710000
0*
#3720000
b10110000 :
1*
#3730000
0*
#3740000
b10110001 :
1*
#3750000
0*
#3760000
b10110010 :
1*
#3770000
0*
#3780000
b10110011 :
1*
#3790000
0*
#3800000
b10110100 :
1*
#3810000
0*
#3820000
b10110101 :
1*
#3830000
0*
#3840000
b10110110 :
1*
#3850000
0*
#3860000
b10110111 :
1*
#3870000
0*
#3880000
b10111000 :
1*
#3890000
0*
#3900000
b10111001 :
1*
#3910000
0*
#3920000
b10111010 :
1*
#3930000
0*
#3940000
b10111011 :
1*
#3950000
0*
#3960000
b10111100 :
1*
#3970000
0*
#3980000
b10111101 :
1*
#3990000
0*
#4000000
b10111110 :
1*
#4010000
0*
#4020000
b10111111 :
1*
#4030000
0*
#4040000
b11000000 :
1*
#4050000
0*
#4060000
b11000001 :
1*
#4070000
0*
#4080000
b11000010 :
1*
#4090000
0*
#4100000
b11000011 :
1*
#4110000
0*
#4120000
b11000100 :
1*
#4130000
0*
#4140000
b11000101 :
1*
#4150000
0*
#4160000
b11000110 :
1*
#4170000
0*
#4180000
b11000111 :
1*
#4190000
0*
#4200000
b11001000 :
1*
#4210000
0*
#4220000
b11001001 :
1*
#4230000
0*
#4240000
b11001010 :
1*
#4250000
0*
#4260000
b11001011 :
1*
#4270000
0*
#4280000
b11001100 :
1*
#4290000
0*
#4300000
b11001101 :
1*
#4310000
0*
#4320000
b11001110 :
1*
#4330000
0*
#4340000
b11001111 :
1*
#4350000
0*
#4360000
b11010000 :
1*
#4370000
0*
#4380000
b11010001 :
1*
#4390000
0*
#4400000
b11010010 :
1*
#4410000
0*
#4420000
b11010011 :
1*
#4430000
0*
#4440000
b11010100 :
1*
#4450000
0*
#4460000
b11010101 :
1*
#4470000
0*
#4480000
b11010110 :
1*
#4490000
0*
#4500000
b11010111 :
1*
#4510000
0*
#4520000
b11011000 :
1*
#4530000
0*
#4540000
b11011001 :
1*
#4550000
0*
#4560000
b10 ?
0>
b0 :
1*
#4570000
0*
#4580000
b1 :
1*
#4590000
0*
#4600000
b10 :
1*
#4610000
0*
#4620000
b11 :
1*
#4630000
0*
#4640000
b100 :
1*
#4650000
0*
#4660000
b101 :
1*
#4670000
0*
#4680000
b110 :
1*
#4690000
0*
#4700000
b111 :
1*
#4710000
0*
#4720000
b1000 :
1*
#4730000
0*
#4740000
b1001 :
1*
#4750000
0*
#4760000
b1010 :
1*
#4770000
0*
#4780000
b1011 :
1*
#4790000
0*
#4800000
b1100 :
1*
#4810000
0*
#4820000
b1101 :
1*
#4830000
0*
#4840000
b1110 :
1*
#4850000
0*
#4860000
b1111 :
1*
#4870000
0*
#4880000
b10000 :
1*
#4890000
0*
#4900000
b10001 :
1*
#4910000
0*
#4920000
b10010 :
1*
#4930000
0*
#4940000
b10011 :
1*
#4950000
0*
#4960000
b10100 :
1*
#4970000
0*
#4980000
b10101 :
1*
#4990000
0*
#5000000
b10110 :
1*
#5010000
0*
#5020000
b10111 :
1*
#5030000
0*
#5040000
b11000 :
1*
#5050000
0*
#5060000
b11001 :
1*
#5070000
0*
#5080000
b11010 :
1*
#5090000
0*
#5100000
b11011 :
1*
#5110000
0*
#5120000
b11100 :
1*
#5130000
0*
#5140000
b11101 :
1*
#5150000
0*
#5160000
b11110 :
1*
#5170000
0*
#5180000
b11111 :
1*
#5190000
0*
#5200000
b100000 :
1*
#5210000
0*
#5220000
b100001 :
1*
#5230000
0*
#5240000
b100010 :
1*
#5250000
0*
#5260000
b100011 :
1*
#5270000
0*
#5280000
b100100 :
1*
#5290000
0*
#5300000
b100101 :
1*
#5310000
0*
#5320000
b100110 :
1*
#5330000
0*
#5340000
b100111 :
1*
#5350000
0*
#5360000
b101000 :
1*
#5370000
0*
#5380000
b101001 :
1*
#5390000
0*
#5400000
b101010 :
1*
#5410000
0*
#5420000
b101011 :
1*
#5430000
0*
#5440000
b101100 :
1*
#5450000
0*
#5460000
b101101 :
1*
#5470000
0*
#5480000
b101110 :
1*
#5490000
0*
#5500000
b101111 :
1*
#5510000
0*
#5520000
b110000 :
1*
#5530000
0*
#5540000
b110001 :
1*
#5550000
0*
#5560000
b110010 :
1*
#5570000
0*
#5580000
b110011 :
1*
#5590000
0*
#5600000
b110100 :
1*
#5610000
0*
#5620000
b110101 :
1*
#5630000
0*
#5640000
b110110 :
1*
#5650000
0*
#5660000
b110111 :
1*
#5670000
0*
#5680000
b111000 :
1*
#5690000
0*
#5700000
b111001 :
1*
#5710000
0*
#5720000
b111010 :
1*
#5730000
0*
#5740000
b111011 :
1*
#5750000
0*
#5760000
b111100 :
1*
#5770000
0*
#5780000
b111101 :
1*
#5790000
0*
#5800000
b111110 :
1*
#5810000
0*
#5820000
b111111 :
1*
#5830000
0*
#5840000
b1000000 :
1*
#5850000
0*
#5860000
b1000001 :
1*
#5870000
0*
#5880000
b1000010 :
1*
#5890000
0*
#5900000
b1000011 :
1*
#5910000
0*
#5920000
b1000100 :
1*
#5930000
0*
#5940000
b1000101 :
1*
#5950000
0*
#5960000
b1000110 :
1*
#5970000
0*
#5980000
b1000111 :
1*
#5990000
0*
#6000000
b1001000 :
1*
#6010000
0*
#6020000
b1001001 :
1*
#6030000
0*
#6040000
b1001010 :
1*
#6050000
0*
#6060000
b1001011 :
1*
#6070000
0*
#6080000
b1001100 :
1*
#6090000
0*
#6100000
b1001101 :
1*
#6110000
0*
#6120000
b1001110 :
1*
#6130000
0*
#6140000
b1001111 :
1*
#6150000
0*
#6160000
b1010000 :
1*
#6170000
0*
#6180000
b1010001 :
1*
#6190000
0*
#6200000
b1010010 :
1*
#6210000
0*
#6220000
b1010011 :
1*
#6230000
0*
#6240000
b1010100 :
1*
#6250000
0*
#6260000
b1010101 :
1*
#6270000
0*
#6280000
b1010110 :
1*
#6290000
0*
#6300000
b1010111 :
1*
#6310000
0*
#6320000
b1011000 :
1*
#6330000
0*
#6340000
b1011001 :
1*
#6350000
0*
#6360000
b1011010 :
1*
#6370000
0*
#6380000
b1011011 :
1*
#6390000
0*
#6400000
b1011100 :
1*
#6410000
0*
#6420000
b1011101 :
1*
#6430000
0*
#6440000
b1011110 :
1*
#6450000
0*
#6460000
b1011111 :
1*
#6470000
0*
#6480000
b1100000 :
1*
#6490000
0*
#6500000
b1100001 :
1*
#6510000
0*
#6520000
b1100010 :
1*
#6530000
0*
#6540000
b1100011 :
1*
#6550000
0*
#6560000
b1100100 :
1*
#6570000
0*
#6580000
b1100101 :
1*
#6590000
0*
#6600000
b1100110 :
1*
#6610000
0*
#6620000
b1100111 :
1*
#6630000
0*
#6640000
b1101000 :
1*
#6650000
0*
#6660000
b1101001 :
1*
#6670000
0*
#6680000
b1101010 :
1*
#6690000
0*
#6700000
b1101011 :
1*
#6710000
0*
#6720000
b1101100 :
1*
#6730000
0*
#6740000
b1101101 :
1*
#6750000
0*
#6760000
b1101110 :
1*
#6770000
0*
#6780000
b1101111 :
1*
#6790000
0*
#6800000
b1110000 :
1*
#6810000
0*
#6820000
b1110001 :
1*
#6830000
0*
#6840000
b1110010 :
1*
#6850000
0*
#6860000
b1110011 :
1*
#6870000
0*
#6880000
b1110100 :
1*
#6890000
0*
#6900000
b1110101 :
1*
#6910000
0*
#6920000
b1110110 :
1*
#6930000
0*
#6940000
b1110111 :
1*
#6950000
0*
#6960000
b1111000 :
1*
#6970000
0*
#6980000
b1111001 :
1*
#6990000
0*
#7000000
b1111010 :
1*
#7010000
0*
#7020000
b1111011 :
1*
#7030000
0*
#7040000
b1111100 :
1*
#7050000
0*
#7060000
b1111101 :
1*
#7070000
0*
#7080000
b1111110 :
1*
#7090000
0*
#7100000
b1111111 :
1*
#7110000
0*
#7120000
b10000000 :
1*
#7130000
0*
#7140000
b10000001 :
1*
#7150000
0*
#7160000
b10000010 :
1*
#7170000
0*
#7180000
b10000011 :
1*
#7190000
0*
#7200000
b10000100 :
1*
#7210000
0*
#7220000
b10000101 :
1*
#7230000
0*
#7240000
b10000110 :
1*
#7250000
0*
#7260000
b10000111 :
1*
#7270000
0*
#7280000
b10001000 :
1*
#7290000
0*
#7300000
b10001001 :
1*
#7310000
0*
#7320000
b10001010 :
1*
#7330000
0*
#7340000
b10001011 :
1*
#7350000
0*
#7360000
b10001100 :
1*
#7370000
0*
#7380000
b10001101 :
1*
#7390000
0*
#7400000
b10001110 :
1*
#7410000
0*
#7420000
b10001111 :
1*
#7430000
0*
#7440000
b10010000 :
1*
#7450000
0*
#7460000
b10010001 :
1*
#7470000
0*
#7480000
b10010010 :
1*
#7490000
0*
#7500000
b10010011 :
1*
#7510000
0*
#7520000
b10010100 :
1*
#7530000
0*
#7540000
b10010101 :
1*
#7550000
0*
#7560000
b10010110 :
1*
#7570000
0*
#7580000
b10010111 :
1*
#7590000
0*
#7600000
b10011000 :
1*
#7610000
0*
#7620000
b10011001 :
1*
#7630000
0*
#7640000
b10011010 :
1*
#7650000
0*
#7660000
b10011011 :
1*
#7670000
0*
#7680000
b10011100 :
1*
#7690000
0*
#7700000
b10011101 :
1*
#7710000
0*
#7720000
b10011110 :
1*
#7730000
0*
#7740000
b10011111 :
1*
#7750000
0*
#7760000
b10100000 :
1*
#7770000
0*
#7780000
b10100001 :
1*
#7790000
0*
#7800000
b10100010 :
1*
#7810000
0*
#7820000
b10100011 :
1*
#7830000
0*
#7840000
b10100100 :
1*
#7850000
0*
#7860000
b10100101 :
1*
#7870000
0*
#7880000
b10100110 :
1*
#7890000
0*
#7900000
b10100111 :
1*
#7910000
0*
#7920000
b10101000 :
1*
#7930000
0*
#7940000
b10101001 :
1*
#7950000
0*
#7960000
b10101010 :
1*
#7970000
0*
#7980000
b10101011 :
1*
#7990000
0*
#8000000
b10101100 :
1*
#8010000
0*
#8020000
b10101101 :
1*
#8030000
0*
#8040000
b10101110 :
1*
#8050000
0*
#8060000
b10101111 :
1*
#8070000
0*
#8080000
b10110000 :
1*
#8090000
0*
#8100000
b10110001 :
1*
#8110000
0*
#8120000
b10110010 :
1*
#8130000
0*
#8140000
b10110011 :
1*
#8150000
0*
#8160000
b10110100 :
1*
#8170000
0*
#8180000
b10110101 :
1*
#8190000
0*
#8200000
b10110110 :
1*
#8210000
0*
#8220000
b10110111 :
1*
#8230000
0*
#8240000
b10111000 :
1*
#8250000
0*
#8260000
b10111001 :
1*
#8270000
0*
#8280000
b10111010 :
1*
#8290000
0*
#8300000
b10111011 :
1*
#8310000
0*
#8320000
b10111100 :
1*
#8330000
0*
#8340000
b10111101 :
1*
#8350000
0*
#8360000
b10111110 :
1*
#8370000
0*
#8380000
b10111111 :
1*
#8390000
0*
#8400000
b11000000 :
1*
#8410000
0*
#8420000
b11000001 :
1*
#8430000
0*
#8440000
b11000010 :
1*
#8450000
0*
#8460000
b11000011 :
1*
#8470000
0*
#8480000
b11000100 :
1*
#8490000
0*
#8500000
b11000101 :
1*
#8510000
0*
#8520000
b11000110 :
1*
#8530000
0*
#8540000
b11000111 :
1*
#8550000
0*
#8560000
b11001000 :
1*
#8570000
0*
#8580000
b11001001 :
1*
#8590000
0*
#8600000
b11001010 :
1*
#8610000
0*
#8620000
b11001011 :
1*
#8630000
0*
#8640000
b11001100 :
1*
#8650000
0*
#8660000
b11001101 :
1*
#8670000
0*
#8680000
b11001110 :
1*
#8690000
0*
#8700000
b11001111 :
1*
#8710000
0*
#8720000
b11010000 :
1*
#8730000
0*
#8740000
b11010001 :
1*
#8750000
0*
#8760000
b11010010 :
1*
#8770000
0*
#8780000
b11010011 :
1*
#8790000
0*
#8800000
b11010100 :
1*
#8810000
0*
#8820000
b11010101 :
1*
#8830000
0*
#8840000
b11010110 :
1*
#8850000
0*
#8860000
b11010111 :
1*
#8870000
0*
#8880000
b11011000 :
1*
1,
b0 B
#8890000
0*
#8900000
b11011001 :
1*
#8910000
0*
#8920000
b11011010 :
1*
#8930000
0*
#8940000
b11011011 :
1*
#8950000
0*
#8960000
b11011100 :
1*
#8970000
0*
#8980000
b11011101 :
1*
#8990000
0*
#9000000
b11011110 :
1*
#9010000
0*
#9020000
b11011111 :
1*
#9030000
0*
#9040000
b11100000 :
1*
#9050000
0*
#9060000
b11100001 :
1*
#9070000
0*
#9080000
b11100010 :
1*
#9090000
0*
#9100000
b11100011 :
1*
#9110000
0*
#9120000
b11100100 :
1*
#9130000
0*
#9140000
b11100101 :
1*
#9150000
0*
#9160000
b11100110 :
1*
#9170000
0*
#9180000
b11100111 :
1*
#9190000
0*
#9200000
b11101000 :
1*
#9210000
0*
#9220000
b11101001 :
1*
#9230000
0*
#9240000
b11101010 :
1*
#9250000
0*
#9260000
b11101011 :
1*
#9270000
0*
#9280000
b11101100 :
1*
#9290000
0*
#9300000
b11101101 :
1*
#9310000
0*
#9320000
b11101110 :
1*
#9330000
0*
#9340000
b11101111 :
1*
#9350000
0*
#9360000
b11110000 :
1*
#9370000
0*
#9380000
b11110001 :
1*
#9390000
0*
#9400000
b11110010 :
1*
#9410000
0*
#9420000
b11110011 :
1*
#9430000
0*
#9440000
b11110100 :
1*
#9450000
0*
#9460000
b11110101 :
1*
#9470000
0*
#9480000
b11110110 :
1*
#9490000
0*
#9500000
b11110111 :
1*
#9510000
0*
#9520000
b11111000 :
1*
#9530000
0*
#9540000
b11111001 :
1*
#9550000
0*
#9560000
b11111010 :
1*
#9570000
0*
#9580000
b11111011 :
1*
#9590000
0*
#9600000
b11111100 :
1*
#9610000
0*
#9620000
b11111101 :
1*
#9630000
0*
#9640000
b11111110 :
1*
#9650000
0*
#9660000
b11111111 :
1*
#9670000
0*
#9680000
b100000000 :
1*
#9690000
0*
#9700000
b100000001 :
1*
#9710000
0*
#9720000
b100000010 :
1*
#9730000
0*
#9740000
b100000011 :
1*
#9750000
0*
#9760000
b100000100 :
1*
#9770000
0*
#9780000
b100000101 :
1*
#9790000
0*
#9800000
b100000110 :
1*
#9810000
0*
#9820000
b100000111 :
1*
#9830000
0*
#9840000
b100001000 :
1*
#9850000
0*
#9860000
b100001001 :
1*
#9870000
0*
#9880000
b100001010 :
1*
#9890000
0*
#9900000
b100001011 :
1*
#9910000
0*
#9920000
b100001100 :
1*
#9930000
0*
#9940000
b100001101 :
1*
#9950000
0*
#9960000
b100001110 :
1*
#9970000
0*
#9980000
b100001111 :
1*
#9990000
0*
#10000000
b100010000 :
1*
#10010000
0*
#10020000
b100010001 :
1*
#10030000
0*
#10040000
b100010010 :
1*
#10050000
0*
#10060000
b100010011 :
1*
#10070000
0*
#10080000
b100010100 :
1*
#10090000
0*
#10100000
b100010101 :
1*
#10110000
0*
#10120000
b100010110 :
1*
#10130000
0*
#10140000
b100010111 :
1*
#10150000
0*
