tx_uart.v
/*
Author: Mario Akira
Date:03/2026
*/
module tx_uart #(
    parameter CLK_FREQ  = 50000000,
    parameter BAUD_RATE = 115200,
    parameter STOP_BITS = 2'h1,           // 1 ou 2
    parameter PARITY    = 1'b0       // "NONE"=0, "EVEN"=1, "ODD"=2
)(
	input 	wire 			clk_IN,
	input 	wire 			rst_IN,

	input 	wire [7:0] 	data_IN,
	input 	wire 			enable_IN,

	output 	reg 			tx_OUT,
	output 	reg 			busy_OUT
);
//=======================================================
//  Local parameters declarations
//=======================================================
	localparam 	CLKS_PER_BIT = CLK_FREQ / BAUD_RATE;
	localparam	idle=2'h0,word_build=2'h1,sending_word=2'h2; 
//=======================================================
//  Refisters declarations
//=======================================================
	reg [11:0] 	tx_shift = 12'hFFF;
	reg [15:0] 	clk_count = 16'h0;
	reg [3:0] 	bit_index = 4'h0;
	reg [3:0] 	total_bits = 4'h0;
	reg [7:0]	data_reg;
	reg 			sending = 1'h0;
	reg 			parity_bit;
	reg [2:0]	next_state;
	reg 			parity_end = 1'b0;
//=======================================================
//  Wire declarations
//=======================================================

//=======================================================
//  Structural coding
//=======================================================
always @(posedge clk_IN) begin
        if (rst_IN) begin
            next_state <= idle;
            tx_OUT <= 1'b1;
            busy_OUT <= 1'b0;
            clk_count <= 16'h0;
            bit_index <= 4'h0;
            tx_shift <= 12'hFFF;
            parity_bit <= 1'b0;
        end 
		  else begin
            case (next_state)
                idle: begin
                    tx_OUT <= 1'b1;
                    busy_OUT <= 1'b0;

                    if (enable_IN) begin
                        data_reg <= data_IN;
                        busy_OUT <= 1'b1;
                        next_state <= word_build;
                    end
						  else begin
								next_state <= idle;
						  end
                end
                word_build: begin
                    if (PARITY == 2'h1) begin
                        parity_bit <= ^data_reg;
                    end else if (PARITY == 2'h2) begin
                        parity_bit <= ~(^data_reg);
                    end else begin
                        parity_bit <= 1'b0;
                    end
                    if (PARITY == 0) begin
                        tx_shift <= { {STOP_BITS{1'b1}}, data_reg, 1'b0 };
                        total_bits <= 4'h1 + 4'h8 + STOP_BITS;
                    end else begin
                        tx_shift <= { {STOP_BITS{1'b1}}, parity_bit, data_reg, 1'b0 };
                        total_bits <= 4'h1 + 4'h8 + 4'h1 + STOP_BITS;
                    end
                    clk_count <= 16'h0;
                    bit_index <= 4'h0;
                    next_state <= sending_word;
                end
                sending_word: begin
                    if (clk_count < CLKS_PER_BIT - 1'b1) begin
                        clk_count <= clk_count + 1'b1;
                    end else begin
                        clk_count <= 16'h0;
                        tx_OUT <= tx_shift[0];
                        tx_shift <= {1'b1, tx_shift[11:1]};
                        if (bit_index < total_bits - 1) begin
                            bit_index <= bit_index + 1;
                        end else begin
                            next_state <= idle;
                        end
                    end
                end

            endcase
        end
    end
endmodule

tb/tx_uart_tb.v
`timescale 1ns/1ns

module tx_uart_tb;

    reg clk;
    reg rst;
    reg start;
    reg [7:0] data_in;

    wire tx;
    wire busy;

    // module call
    tx_uart #(
        .CLK_FREQ(50000000),
        .BAUD_RATE(115200),
        .STOP_BITS(1),
        .PARITY(0)
    ) uut (
        .clk_IN(clk),
        .rst_IN(rst),
        .data_IN(data_in),
        .enable_IN(start),
        .tx_OUT(tx),
        .busy_OUT(busy)
    );

    // Clock 50MHz
    initial begin
	clk = 1'b1;
	forever #10 clk=~clk;
    end

    initial begin
        // GTKWave files
        $dumpfile("uart_tx.vcd");
        $dumpvars(0, tx_uart_tb);

        // Initial data
        rst = 1;
        start = 0;
        data_in = 8'h00;

        #200;
        rst = 0;

        // Envia 0x55 (01010101)
        send_byte(8'h55);

        #200000;

        // Envia 0xA3
        send_byte(8'hA3);

        #200000;

        $finish;
    end

    // Task para enviar byte
    task send_byte(input [7:0] data);
    begin
        @(posedge clk);
        data_in <= data;
        start <= 1;

        @(posedge clk);
        start <= 0;

        // espera terminar transmissão
        wait (busy == 0);
    end
    endtask

endmodule

tb/uart_tx.vcd
$date
	Thu Mar 19 21:47:31 2026
$end
$version
	Icarus Verilog
$end
$timescale
	1ns
$end
$scope module tx_uart_tb $end
$var wire 1 ! tx $end
$var wire 1 " busy $end
$var reg 1 # clk $end
$var reg 8 $ data_in [7:0] $end
$var reg 1 % rst $end
$var reg 1 & start $end
$scope module uut $end
$var wire 1 # clk_IN $end
$var wire 8 ' data_IN [7:0] $end
$var wire 1 & enable_IN $end
$var wire 1 % rst_IN $end
$var parameter 32 ( BAUD_RATE $end
$var parameter 32 ) CLKS_PER_BIT $end
$var parameter 32 * CLK_FREQ $end
$var parameter 32 + PARITY $end
$var parameter 32 , STOP_BITS $end
$var parameter 2 - idle $end
$var parameter 2 . sending_word $end
$var parameter 2 / word_build $end
$var reg 4 0 bit_index [3:0] $end
$var reg 1 " busy_OUT $end
$var reg 16 1 clk_count [15:0] $end
$var reg 8 2 data_reg [7:0] $end
$var reg 3 3 next_state [2:0] $end
$var reg 1 4 parity_bit $end
$var reg 1 5 parity_end $end
$var reg 1 6 sending $end
$var reg 4 7 total_bits [3:0] $end
$var reg 1 ! tx_OUT $end
$var reg 12 8 tx_shift [11:0] $end
$upscope $end
$scope task send_byte $end
$var reg 8 9 data [7:0] $end
$upscope $end
$upscope $end
$enddefinitions $end
$comment Show the parameter values. $end
$dumpall
b1 /
b10 .
b0 -
b1 ,
b0 +
b10111110101111000010000000 *
b110110010 )
b11100001000000000 (
$end
#0
$dumpvars
bx 9
b111111111111 8
b0 7
06
05
04
b0 3
bx 2
b0 1
b0 0
b0 '
0&
1%
b0 $
1#
0"
1!
$end
#10
0#
#20
1#
#30
0#
#40
1#
#50
0#
#60
1#
#70
0#
#80
1#
#90
0#
#100
1#
#110
0#
#120
1#
#130
0#
#140
1#
#150
0#
#160
1#
#170
0#
#180
1#
#190
0#
#200
1&
b1010101 $
b1010101 '
1#
b1010101 9
0%
#210
0#
#220
0&
b1 3
1"
b1010101 2
1#
#230
0#
#240
b10 3
b1010 7
b1010101010 8
1#
#250
0#
#260
b1 1
1#
#270
0#
#280
b10 1
1#
#290
0#
#300
b11 1
1#
#310
0#
#320
b100 1
1#
#330
0#
#340
b101 1
1#
#350
0#
#360
b110 1
1#
#370
0#
#380
b111 1
1#
#390
0#
#400
b1000 1
1#
#410
0#
#420
b1001 1
1#
#430
0#
#440
b1010 1
1#
#450
0#
#460
b1011 1
1#
#470
0#
#480
b1100 1
1#
#490
0#
#500
b1101 1
1#
#510
0#
#520
b1110 1
1#
#530
0#
#540
b1111 1
1#
#550
0#
#560
b10000 1
1#
#570
0#
#580
b10001 1
1#
#590
0#
#600
b10010 1
1#
#610
0#
#620
b10011 1
1#
#630
0#
#640
b10100 1
1#
#650
0#
#660
b10101 1
1#
#670
0#
#680
b10110 1
1#
#690
0#
#700
b10111 1
1#
#710
0#
#720
b11000 1
1#
#730
0#
#740
b11001 1
1#
#750
0#
#760
b11010 1
1#
#770
0#
#780
b11011 1
1#
#790
0#
#800
b11100 1
1#
#810
0#
#820
b11101 1
1#
#830
0#
#840
b11110 1
1#
#850
0#
#860
b11111 1
1#
#870
0#
#880
b100000 1
1#
#890
0#
#900
b100001 1
1#
#910
0#
#920
b100010 1
1#
#930
0#
#940
b100011 1
1#
#950
0#
#960
b100100 1
1#
#970
0#
#980
b100101 1
1#
#990
0#
#1000
b100110 1
1#
#1010
0#
#1020
b100111 1
1#
#1030
0#
#1040
b101000 1
1#
#1050
0#
#1060
b101001 1
1#
#1070
0#
#1080
b101010 1
1#
#1090
0#
#1100
b101011 1
1#
#1110
0#
#1120
b101100 1
1#
#1130
0#
#1140
b101101 1
1#
#1150
0#
#1160
b101110 1
1#
#1170
0#
#1180
b101111 1
1#
#1190
0#
#1200
b110000 1
1#
#1210
0#
#1220
b110001 1
1#
#1230
0#
#1240
b110010 1
1#
#1250
0#
#1260
b110011 1
1#
#1270
0#
#1280
b110100 1
1#
#1290
0#
#1300
b110101 1
1#
#1310
0#
#1320
b110110 1
1#
#1330
0#
#1340
b110111 1
1#
#1350
0#
#1360
b111000 1
1#
#1370
0#
#1380
b111001 1
1#
#1390
0#
#1400
b111010 1
1#
#1410
0#
#1420
b111011 1
1#
#1430
0#
#1440
b111100 1
1#
#1450
0#
#1460
b111101 1
1#
#1470
0#
#1480
b111110 1
1#
#1490
0#
#1500
b111111 1
1#
#1510
0#
#1520
b1000000 1
1#
#1530
0#
#1540
b1000001 1
1#
#1550
0#
#1560
b1000010 1
1#
#1570
0#
#1580
b1000011 1
1#
#1590
0#
#1600
b1000100 1
1#
#1610
0#
#1620
b1000101 1
1#
#1630
0#
#1640
b1000110 1
1#
#1650
0#
#1660
b1000111 1
1#
#1670
0#
#1680
b1001000 1
1#
#1690
0#
#1700
b1001001 1
1#
#1710
0#
#1720
b1001010 1
1#
#1730
0#
#1740
b1001011 1
1#
#1750
0#
#1760
b1001100 1
1#
#1770
0#
#1780
b1001101 1
1#
#1790
0#
#1800
b1001110 1
1#
#1810
0#
#1820
b1001111 1
1#
#1830
0#
#1840
b1010000 1
1#
#1850
0#
#1860
b1010001 1
1#
#1870
0#
#1880
b1010010 1
1#
#1890
0#
#1900
b1010011 1
1#
#1910
0#
#1920
b1010100 1
1#
#1930
0#
#1940
b1010101 1
1#
#1950
0#
#1960
b1010110 1
1#
#1970
0#
#1980
b1010111 1
1#
#1990
0#
#2000
b1011000 1
1#
#2010
0#
#2020
b1011001 1
1#
#2030
0#
#2040
b1011010 1
1#
#2050
0#
#2060
b1011011 1
1#
#2070
0#
#2080
b1011100 1
1#
#2090
0#
#2100
b1011101 1
1#
#2110
0#
#2120
b1011110 1
1#
#2130
0#
#2140
b1011111 1
1#
#2150
0#
#2160
b1100000 1
1#
#2170
0#
#2180
b1100001 1
1#
#2190
0#
#2200
b1100010 1
1#
#2210
0#
#2220
b1100011 1
1#
#2230
0#
#2240
b1100100 1
1#
#2250
0#
#2260
b1100101 1
1#
#2270
0#
#2280
b1100110 1
1#
#2290
0#
#2300
b1100111 1
1#
#2310
0#
#2320
b1101000 1
1#
#2330
0#
#2340
b1101001 1
1#
#2350
0#
#2360
b1101010 1
1#
#2370
0#
#2380
b1101011 1
1#
#2390
0#
#2400
b1101100 1
1#
#2410
0#
#2420
b1101101 1
1#
#2430
0#
#2440
b1101110 1
1#
#2450
0#
#2460
b1101111 1
1#
#2470
0#
#2480
b1110000 1
1#
#2490
0#
#2500
b1110001 1
1#
#2510
0#
#2520
b1110010 1
1#
#2530
0#
#2540
b1110011 1
1#
#2550
0#
#2560
b1110100 1
1#
#2570
0#
#2580
b1110101 1
1#
#2590
0#
#2600
b1110110 1
1#
#2610
0#
#2620
b1110111 1
1#
#2630
0#
#2640
b1111000 1
1#
#2650
0#
#2660
b1111001 1
1#
#2670
0#
#2680
b1111010 1
1#
#2690
0#
#2700
b1111011 1
1#
#2710
0#
#2720
b1111100 1
1#
#2730
0#
#2740
b1111101 1
1#
#2750
0#
#2760
b1111110 1
1#
#2770
0#
#2780
b1111111 1
1#
#2790
0#
#2800
b10000000 1
1#
#2810
0#
#2820
b10000001 1
1#
#2830
0#
#2840
b10000010 1
1#
#2850
0#
#2860
b10000011 1
1#
#2870
0#
#2880
b10000100 1
1#
#2890
0#
#2900
b10000101 1
1#
#2910
0#
#2920
b10000110 1
1#
#2930
0#
#2940
b10000111 1
1#
#2950
0#
#2960
b10001000 1
1#
#2970
0#
#2980
b10001001 1
1#
#2990
0#
#3000
b10001010 1
1#
#3010
0#
#3020
b10001011 1
1#
#3030
0#
#3040
b10001100 1
1#
#3050
0#
#3060
b10001101 1
1#
#3070
0#
#3080
b10001110 1
1#
#3090
0#
#3100
b10001111 1
1#
#3110
0#
#3120
b10010000 1
1#
#3130
0#
#3140
b10010001 1
1#
#3150
0#
#3160
b10010010 1
1#
#3170
0#
#3180
b10010011 1
1#
#3190
0#
#3200
b10010100 1
1#
#3210
0#
#3220
b10010101 1
1#
#3230
0#
#3240
b10010110 1
1#
#3250
0#
#3260
b10010111 1
1#
#3270
0#
#3280
b10011000 1
1#
#3290
0#
#3300
b10011001 1
1#
#3310
0#
#3320
b10011010 1
1#
#3330
0#
#3340
b10011011 1
1#
#3350
0#
#3360
b10011100 1
1#
#3370
0#
#3380
b10011101 1
1#
#3390
0#
#3400
b10011110 1
1#
#3410
0#
#3420
b10011111 1
1#
#3430
0#
#3440
b10100000 1
1#
#3450
0#
#3460
b10100001 1
1#
#3470
0#
#3480
b10100010 1
1#
#3490
0#
#3500
b10100011 1
1#
#3510
0#
#3520
b10100100 1
1#
#3530
0#
#3540
b10100101 1
1#
#3550
0#
#3560
b10100110 1
1#
#3570
0#
#3580
b10100111 1
1#
#3590
0#
#3600
b10101000 1
1#
#3610
0#
#3620
b10101001 1
1#
#3630
0#
#3640
b10101010 1
1#
#3650
0#
#3660
b10101011 1
1#
#3670
0#
#3680
b10101100 1
1#
#3690
0#
#3700
b10101101 1
1#
#3710
0#
#3720
b10101110 1
1#
#3730
0#
#3740
b10101111 1
1#
#3750
0#
#3760
b10110000 1
1#
#3770
0#
#3780
b10110001 1
1#
#3790
0#
#3800
b10110010 1
1#
#3810
0#
#3820
b10110011 1
1#
#3830
0#
#3840
b10110100 1
1#
#3850
0#
#3860
b10110101 1
1#
#3870
0#
#3880
b10110110 1
1#
#3890
0#
#3900
b10110111 1
1#
#3910
0#
#3920
b10111000 1
1#
#3930
0#
#3940
b10111001 1
1#
#3950
0#
#3960
b10111010 1
1#
#3970
0#
#3980
b10111011 1
1#
#3990
0#
#4000
b10111100 1
1#
#4010
0#
#4020
b10111101 1
1#
#4030
0#
#4040
b10111110 1
1#
#4050
0#
#4060
b10111111 1
1#
#4070
0#
#4080
b11000000 1
1#
#4090
0#
#4100
b11000001 1
1#
#4110
0#
#4120
b11000010 1
1#
#4130
0#
#4140
b11000011 1
1#
#4150
0#
#4160
b11000100 1
1#
#4170
0#
#4180
b11000101 1
1#
#4190
0#
#4200
b11000110 1
1#
#4210
0#
#4220
b11000111 1
1#
#4230
0#
#4240
b11001000 1
1#
#4250
0#
#4260
b11001001 1
1#
#4270
0#
#4280
b11001010 1
1#
#4290
0#
#4300
b11001011 1
1#
#4310
0#
#4320
b11001100 1
1#
#4330
0#
#4340
b11001101 1
1#
#4350
0#
#4360
b11001110 1
1#
#4370
0#
#4380
b11001111 1
1#
#4390
0#
#4400
b11010000 1
1#
#4410
0#
#4420
b11010001 1
1#
#4430
0#
#4440
b11010010 1
1#
#4450
0#
#4460
b11010011 1
1#
#4470
0#
#4480
b11010100 1
1#
#4490
0#
#4500
b11010101 1
1#
#4510
0#
#4520
b11010110 1
1#
#4530
0#
#4540
b11010111 1
1#
#4550
0#
#4560
b11011000 1
1#
#4570
0#
#4580
b11011001 1
1#
#4590
0#
#4600
b11011010 1
1#
#4610
0#
#4620
b11011011 1
1#
#4630
0#
#4640
b11011100 1
1#
#4650
0#
#4660
b11011101 1
1#
#4670
0#
#4680
b11011110 1
1#
#4690
0#
#4700
b11011111 1
1#
#4710
0#
#4720
b11100000 1
1#
#4730
0#
#4740
b11100001 1
1#
#4750
0#
#4760
b11100010 1
1#
#4770
0#
#4780
b11100011 1
1#
#4790
0#
#4800
b11100100 1
1#
#4810
0#
#4820
b11100101 1
1#
#4830
0#
#4840
b11100110 1
1#
#4850
0#
#4860
b11100111 1
1#
#4870
0#
#4880
b11101000 1
1#
#4890
0#
#4900
b11101001 1
1#
#4910
0#
#4920
b11101010 1
1#
#4930
0#
#4940
b11101011 1
1#
#4950
0#
#4960
b11101100 1
1#
#4970
0#
#4980
b11101101 1
1#
#4990
0#
#5000
b11101110 1
1#
#5010
0#
#5020
b11101111 1
1#
#5030
0#
#5040
b11110000 1
1#
#5050
0#
#5060
b11110001 1
1#
#5070
0#
#5080
b11110010 1
1#
#5090
0#
#5100
b11110011 1
1#
#5110
0#
#5120
b11110100 1
1#
#5130
0#
#5140
b11110101 1
1#
#5150
0#
#5160
b11110110 1
1#
#5170
0#
#5180
b11110111 1
1#
#5190
0#
#5200
b11111000 1
1#
#5210
0#
#5220
b11111001 1
1#
#5230
0#
#5240
b11111010 1
1#
#5250
0#
#5260
b11111011 1
1#
#5270
0#
#5280
b11111100 1
1#
#5290
0#
#5300
b11111101 1
1#
#5310
0#
#5320
b11111110 1
1#
#5330
0#
#5340
b11111111 1
1#
#5350
0#
#5360
b100000000 1
1#
#5370
0#
#5380
b100000001 1
1#
#5390
0#
#5400
b100000010 1
1#
#5410
0#
#5420
b100000011 1
1#
#5430
0#
#5440
b100000100 1
1#
#5450
0#
#5460
b100000101 1
1#
#5470
0#
#5480
b100000110 1
1#
#5490
0#
#5500
b100000111 1
1#
#5510
0#
#5520
b100001000 1
1#
#5530
0#
#5540
b100001001 1
1#
#5550
0#
#5560
b100001010 1
1#
#5570
0#
#5580
b100001011 1
1#
#5590
0#
#5600
b100001100 1
1#
#5610
0#
#5620
b100001101 1
1#
#5630
0#
#5640
b100001110 1
1#
#5650
0#
#5660
b100001111 1
1#
#5670
0#
#5680
b100010000 1
1#
#5690
0#
#5700
b100010001 1
1#
#5710
0#
#5720
b100010010 1
1#
#5730
0#
#5740
b100010011 1
1#
#5750
0#
#5760
b100010100 1
1#
#5770
0#
#5780
b100010101 1
1#
#5790
0#
#5800
b100010110 1
1#
#5810
0#
#5820
b100010111 1
1#
#5830
0#
#5840
b100011000 1
1#
#5850
0#
#5860
b100011001 1
1#
#5870
0#
#5880
b100011010 1
1#
#5890
0#
#5900
b100011011 1
1#
#5910
0#
#5920
b100011100 1
1#
#5930
0#
#5940
b100011101 1
1#
#5950
0#
#5960
b100011110 1
1#
#5970
0#
#5980
b100011111 1
1#
#5990
0#
#6000
b100100000 1
1#
#6010
0#
#6020
b100100001 1
1#
#6030
0#
#6040
b100100010 1
1#
#6050
0#
#6060
b100100011 1
1#
#6070
0#
#6080
b100100100 1
1#
#6090
0#
#6100
b100100101 1
1#
#6110
0#
#6120
b100100110 1
1#
#6130
0#
#6140
b100100111 1
1#
#6150
0#
#6160
b100101000 1
1#
#6170
0#
#6180
b100101001 1
1#
#6190
0#
#6200
b100101010 1
1#
#6210
0#
#6220
b100101011 1
1#
#6230
0#
#6240
b100101100 1
1#
#6250
0#
#6260
b100101101 1
1#
#6270
0#
#6280
b100101110 1
1#
#6290
0#
#6300
b100101111 1
1#
#6310
0#
#6320
b100110000 1
1#
#6330
0#
#6340
b100110001 1
1#
#6350
0#
#6360
b100110010 1
1#
#6370
0#
#6380
b100110011 1
1#
#6390
0#
#6400
b100110100 1
1#
#6410
0#
#6420
b100110101 1
1#
#6430
0#
#6440
b100110110 1
1#
#6450
0#
#6460
b100110111 1
1#
#6470
0#
#6480
b100111000 1
1#
#6490
0#
#6500
b100111001 1
1#
#6510
0#
#6520
b100111010 1
1#
#6530
0#
#6540
b100111011 1
1#
#6550
0#
#6560
b100111100 1
1#
#6570
0#
#6580
b100111101 1
1#
#6590
0#
#6600
b100111110 1
1#
#6610
0#
#6620
b100111111 1
1#
#6630
0#
#6640
b101000000 1
1#
#6650
0#
#6660
b101000001 1
1#
#6670
0#
#6680
b101000010 1
1#
#6690
0#
#6700
b101000011 1
1#
#6710
0#
#6720
b101000100 1
1#
#6730
0#
#6740
b101000101 1
1#
#6750
0#
#6760
b101000110 1
1#
#6770
0#
#6780
b101000111 1
1#
#6790
0#
#6800
b101001000 1
1#
#6810
0#
#6820
b101001001 1
1#
#6830
0#
#6840
b101001010 1
1#
#6850
0#
#6860
b101001011 1
1#
#6870
0#
#6880
b101001100 1
1#
#6890
0#
#6900
b101001101 1
1#
#6910
0#
#6920
b101001110 1
1#
#6930
0#
#6940
b101001111 1
1#
#6950
0#
#6960
b101010000 1
1#
#6970
0#
#6980
b101010001 1
1#
#6990
0#
#7000
b101010010 1
1#
#7010
0#
#7020
b101010011 1
1#
#7030
0#
#7040
b101010100 1
1#
#7050
0#
#7060
b101010101 1
1#
#7070
0#
#7080
b101010110 1
1#
#7090
0#
#7100
b101010111 1
1#
#7110
0#
#7120
b101011000 1
1#
#7130
0#
#7140
b101011001 1
1#
#7150
0#
#7160
b101011010 1
1#
#7170
0#
#7180
b101011011 1
1#
#7190
0#
#7200
b101011100 1
1#
#7210
0#
#7220
b101011101 1
1#
#7230
0#
#7240
b101011110 1
1#
#7250
0#
#7260
b101011111 1
1#
#7270
0#
#7280
b101100000 1
1#
#7290
0#
#7300
b101100001 1
1#
#7310
0#
#7320
b101100010 1
1#
#7330
0#
#7340
b101100011 1
1#
#7350
0#
#7360
b101100100 1
1#
#7370
0#
#7380
b101100101 1
1#
#7390
0#
#7400
b101100110 1
1#
#7410
0#
#7420
b101100111 1
1#
#7430
0#
#7440
b101101000 1
1#
#7450
0#
#7460
b101101001 1
1#
#7470
0#
#7480
b101101010 1
1#
#7490
0#
#7500
b101101011 1
1#
#7510
0#
#7520
b101101100 1
1#
#7530
0#
#7540
b101101101 1
1#
#7550
0#
#7560
b101101110 1
1#
#7570
0#
#7580
b101101111 1
1#
#7590
0#
#7600
b101110000 1
1#
#7610
0#
#7620
b101110001 1
1#
#7630
0#
#7640
b101110010 1
1#
#7650
0#
#7660
b101110011 1
1#
#7670
0#
#7680
b101110100 1
1#
#7690
0#
#7700
b101110101 1
1#
#7710
0#
#7720
b101110110 1
1#
#7730
0#
#7740
b101110111 1
1#
#7750
0#
#7760
b101111000 1
1#
#7770
0#
#7780
b101111001 1
1#
#7790
0#
#7800
b101111010 1
1#
#7810
0#
#7820
b101111011 1
1#
#7830
0#
#7840
b101111100 1
1#
#7850
0#
#7860
b101111101 1
1#
#7870
0#
#7880
b101111110 1
1#
#7890
0#
#7900
b101111111 1
1#
#7910
0#
#7920
b110000000 1
1#
#7930
0#
#7940
b110000001 1
1#
#7950
0#
#7960
b110000010 1
1#
#7970
0#
#7980
b110000011 1
1#
#7990
0#
#8000
b110000100 1
1#
#8010
0#
#8020
b110000101 1
1#
#8030
0#
#8040
b110000110 1
1#
#8050
0#
#8060
b110000111 1
1#
#8070
0#
#8080
b110001000 1
1#
#8090
0#
#8100
b110001001 1
1#
#8110
0#
#8120
b110001010 1
1#
#8130
0#
#8140
b110001011 1
1#
#8150
0#
#8160
b110001100 1
1#
#8170
0#
#8180
b110001101 1
1#
#8190
0#
#8200
b110001110 1
1#
#8210
0#
#8220
b110001111 1
1#
#8230
0#
#8240
b110010000 1
1#
#8250
0#
#8260
b110010001 1
1#
#8270
0#
#8280
b110010010 1
1#
#8290
0#
#8300
b110010011 1
1#
#8310
0#
#8320
b110010100 1
1#
#8330
0#
#8340
b110010101 1
1#
#8350
0#
#8360
b110010110 1
1#
#8370
0#
#8380
b110010111 1
1#
#8390
0#
#8400
b110011000 1
1#
#8410
0#
#8420
b110011001 1
1#
#8430
0#
#8440
b110011010 1
1#
#8450
0#
#8460
b110011011 1
1#
#8470
0#
#8480
b110011100 1
1#
#8490
0#
#8500
b110011101 1
1#
#8510
0#
#8520
b110011110 1
1#
#8530
0#
#8540
b110011111 1
1#
#8550
0#
#8560
b110100000 1
1#
#8570
0#
#8580
b110100001 1
1#
#8590
0#
#8600
b110100010 1
1#
#8610
0#
#8620
b110100011 1
1#
#8630
0#
#8640
b110100100 1
1#
#8650
0#
#8660
b110100101 1
1#
#8670
0#
#8680
b110100110 1
1#
#8690
0#
#8700
b110100111 1
1#
#8710
0#
#8720
b110101000 1
1#
#8730
0#
#8740
b110101001 1
1#
#8750
0#
#8760
b110101010 1
1#
#8770
0#
#8780
b110101011 1
1#
#8790
0#
#8800
b110101100 1
1#
#8810
0#
#8820
b110101101 1
1#
#8830
0#
#8840
b110101110 1
1#
#8850
0#
#8860
b110101111 1
1#
#8870
0#
#8880
b110110000 1
1#
#8890
0#
#8900
b110110001 1
1#
#8910
0#
#8920
b1 0
b100101010101 8
0!
b0 1
1#
#8930
0#
#8940
b1 1
1#
#8950
0#
#8960
b10 1
1#
#8970
0#
#8980
b11 1
1#
#8990
0#
#9000
b100 1
1#
#9010
0#
#9020
b101 1
1#
#9030
0#
#9040
b110 1
1#
#9050
0#
#9060
b111 1
1#
#9070
0#
#9080
b1000 1
1#
#9090
0#
#9100
b1001 1
1#
#9110
0#
#9120
b1010 1
1#
#9130
0#
#9140
b1011 1
1#
#9150
0#
#9160
b1100 1
1#
#9170
0#
#9180
b1101 1
1#
#9190
0#
#9200
b1110 1
1#
#9210
0#
#9220
b1111 1
1#
#9230
0#
#9240
b10000 1
1#
#9250
0#
#9260
b10001 1
1#
#9270
0#
#9280
b10010 1
1#
#9290
0#
#9300
b10011 1
1#
#9310
0#
#9320
b10100 1
1#
#9330
0#
#9340
b10101 1
1#
#9350
0#
#9360
b10110 1
1#
#9370
0#
#9380
b10111 1
1#
#9390
0#
#9400
b11000 1
1#
#9410
0#
#9420
b11001 1
1#
#9430
0#
#9440
b11010 1
1#
#9450
0#
#9460
b11011 1
1#
#9470
0#
#9480
b11100 1
1#
#9490
0#
#9500
b11101 1
1#
#9510
0#
#9520
b11110 1
1#
#9530
0#
#9540
b11111 1
1#
#9550
0#
#9560
b100000 1
1#
#9570
0#
#9580
b100001 1
1#
#9590
0#
#9600
b100010 1
1#
#9610
0#
#9620
b100011 1
1#
#9630
0#
#9640
b100100 1
1#
#9650
0#
#9660
b100101 1
1#
#9670
0#
#9680
b100110 1
1#
#9690
0#
#9700
b100111 1
1#
#9710
0#
#9720
b101000 1
1#
#9730
0#
#9740
b101001 1
1#
#9750
0#
#9760
b101010 1
1#
#9770
0#
#9780
b101011 1
1#
#9790
0#
#9800
b101100 1
1#
#9810
0#
#9820
b101101 1
1#
#9830
0#
#9840
b101110 1
1#
#9850
0#
#9860
b101111 1
1#
#9870
0#
#9880
b110000 1
1#
#9890
0#
#9900
b110001 1
1#
#9910
0#
#9920
b110010 1
1#
#9930
0#
#9940
b110011 1
1#
#9950
0#
#9960
b110100 1
1#
#9970
0#
#9980
b110101 1
1#
#9990
0#
#10000
b110110 1
1#
#10010
0#
#10020
b110111 1
1#
#10030
0#
#10040
b111000 1
1#
#10050
0#
#10060
b111001 1
1#
#10070
0#
#10080
b111010 1
1#
#10090
0#
#10100
b111011 1
1#
#10110
0#
#10120
b111100 1
1#
#10130
0#
#10140
b111101 1
1#
#10150
0#
#10160
b111110 1
1#
#10170
0#
#10180
b111111 1
1#
#10190
0#
#10200
b1000000 1
1#
#10210
0#
#10220
b1000001 1
1#
#10230
0#
#10240
b1000010 1
1#
#10250
0#
#10260
b1000011 1
1#
#10270
0#
#10280
b1000100 1
1#
#10290
0#
#10300
b1000101 1
1#
#10310
0#
#10320
b1000110 1
1#
#10330
0#
#10340
b1000111 1
1#
#10350
0#
#10360
b1001000 1
1#
#10370
0#
#10380
b1001001 1
1#
#10390
0#
#10400
b1001010 1
1#
#10410
0#
#10420
b1001011 1
1#
#10430
0#
#10440
b1001100 1
1#
#10450
0#
#10460
b1001101 1
1#
#10470
0#
#10480
b1001110 1
1#
#10490
0#
#10500
b1001111 1
1#
#10510
0#
#10520
b1010000 1
1#
#10530
0#
#10540
b1010001 1
1#
#10550
0#
#10560
b1010010 1
1#
#10570
0#
#10580
b1010011 1
1#
#10590
0#
#10600
b1010100 1
1#
#10610
0#
#10620
b1010101 1
1#
#10630
0#
#10640
b1010110 1
1#
#10650
0#
#10660
b1010111 1
1#
#10670
0#
#10680
b1011000 1
1#
#10690
0#
#10700
b1011001 1
1#
#10710
0#
#10720
b1011010 1
1#
#10730
0#
#10740
b1011011 1
1#
#10750
0#
#10760
b1011100 1
1#
#10770
0#
#10780
b1011101 1
1#
#10790
0#
#10800
b1011110 1
1#
#10810
0#
#10820
b1011111 1
1#
#10830
0#
#10840
b1100000 1
1#
#10850
0#
#10860
b1100001 1
1#
#10870
0#
#10880
b1100010 1
1#
#10890
0#
#10900
b1100011 1
1#
#10910
0#
#10920
b1100100 1
1#
#10930
0#
#10940
b1100101 1
1#
#10950
0#
#10960
b1100110 1
1#
#10970
0#
#10980
b1100111 1
1#
#10990
0#
#11000
b1101000 1
1#
#11010
0#
#11020
b1101001 1
1#
#11030
0#
#11040
b1101010 1
1#
#11050
0#
#11060
b1101011 1
1#
#11070
0#
#11080
b1101100 1
1#
#11090
0#
#11100
b1101101 1
1#
#11110
0#
#11120
b1101110 1
1#
#11130
0#
#11140
b1101111 1
1#
#11150
0#
#11160
b1110000 1
1#
#11170
0#
#11180
b1110001 1
1#
#11190
0#
#11200
b1110010 1
1#
#11210
0#
#11220
b1110011 1
1#
#11230
0#
#11240
b1110100 1
1#
#11250
0#
#11260
b1110101 1
1#
#11270
0#
#11280
b1110110 1
1#
#11290
0#
#11300
b1110111 1
1#
#11310
0#
#11320
b1111000 1
1#
#11330
0#
#11340
b1111001 1
1#
#11350
0#
#11360
b1111010 1
1#
#11370
0#
#11380
b1111011 1
1#
#11390
0#
#11400
b1111100 1
1#
#11410
0#
#11420
b1111101 1
1#
#11430
0#
#11440
b1111110 1
1#
#11450
0#
#11460
b1111111 1
1#
#11470
0#
#11480
b10000000 1
1#
#11490
0#
#11500
b10000001 1
1#
#11510
0#
#11520
b10000010 1
1#
#11530
0#
#11540
b10000011 1
1#
#11550
0#
#11560
b10000100 1
1#
#11570
0#
#11580
b10000101 1
1#
#11590
0#
#11600
b10000110 1
1#
#11610
0#
#11620
b10000111 1
1#
#11630
0#
#11640
b10001000 1
1#
#11650
0#
#11660
b10001001 1
1#
#11670
0#
#11680
b10001010 1
1#
#11690
0#
#11700
b10001011 1
1#
#11710
0#
#11720
b10001100 1
1#
#11730
0#
#11740
b10001101 1
1#
#11750
0#
#11760
b10001110 1
1#
#11770
0#
#11780
b10001111 1
1#
#11790
0#
#11800
b10010000 1
1#
#11810
0#
#11820
b10010001 1
1#
#11830
0#
#11840
b10010010 1
1#
#11850
0#
#11860
b10010011 1
1#
#11870
0#
